DockerBuild/DockerBuild.py
DockerBuild/__init__.py
DockerBuild-0.7.1.dist-info/DESCRIPTION.rst
DockerBuild-0.7.1.dist-info/METADATA
DockerBuild-0.7.1.dist-info/RECORD
DockerBuild-0.7.1.dist-info/WHEEL
DockerBuild-0.7.1.dist-info/entry_points.txt
DockerBuild-0.7.1.dist-info/metadata.json
DockerBuild-0.7.1.dist-info/top_level.txt
