Metadata-Version: 2.0
Name: DockerBuild
Version: 0.7.1
Summary: DockerBuild is a 'dockerfile' file generation tools. It converts a file hierarchy tree into a dockerfile.
Home-page: https://github.com/qeyup/DockerBuild
Author: Javier Moreno
Author-email: jgmore@gmail.com
License: UNKNOWN
Platform: UNKNOWN
Requires-Dist: requests
